linkedin_games_solver/__init__.py
linkedin_games_solver/queens_solver.py
linkedin_games_solver/solver.py
linkedin_games_solver/tango_solver.py
linkedin_games_solver/web_scraper.py
linkedin_games_solver/zip_solver.py
linkedin_games_solver-0.1.2.dist-info/licenses/LICENSE
linkedin_games_solver-0.1.2.dist-info/METADATA
linkedin_games_solver-0.1.2.dist-info/WHEEL
linkedin_games_solver-0.1.2.dist-info/entry_points.txt
linkedin_games_solver-0.1.2.dist-info/top_level.txt
linkedin_games_solver-0.1.2.dist-info/RECORD
