Metadata-Version: 2.4
Name: linkedin-games-solver
Version: 0.1.2
Summary: A solver for LinkedIn's puzzle games using Selenium
Home-page: https://github.com/zanebookbinder/LinkedIn-Games-Solver
Author: Zane Bookbinder
Classifier: Programming Language :: Python :: 3
Classifier: Operating System :: OS Independent
Requires-Python: >=3.7
License-File: LICENSE
Requires-Dist: attrs
Requires-Dist: certifi
Requires-Dist: charset-normalizer
Requires-Dist: h11
Requires-Dist: idna
Requires-Dist: outcome
Requires-Dist: PySocks
Requires-Dist: readchar
Requires-Dist: rich
Requires-Dist: selenium
Requires-Dist: sniffio
Requires-Dist: sortedcontainers
Requires-Dist: trio
Requires-Dist: trio-websocket
Requires-Dist: typing_extensions
Requires-Dist: urllib3
Requires-Dist: websocket-client
Requires-Dist: websockets
Requires-Dist: wsproto
Dynamic: author
Dynamic: classifier
Dynamic: description
Dynamic: description-content-type
Dynamic: home-page
Dynamic: license-file
Dynamic: requires-dist
Dynamic: requires-python
Dynamic: summary
